pymdmix_run/__init__.py
pymdmix_run/run.py
pymdmix_run-0.0.2.data/scripts/mdmix-run
pymdmix_run-0.0.2.dist-info/LICENSE
pymdmix_run-0.0.2.dist-info/METADATA
pymdmix_run-0.0.2.dist-info/WHEEL
pymdmix_run-0.0.2.dist-info/top_level.txt
pymdmix_run-0.0.2.dist-info/RECORD
